{"content":[{"id":"128a7132","settings":{"stretch_section":"section-stretched","padding":{"unit":"px","top":"80","right":"0","bottom":"80","left":"0","isLinked":false},"structure":"20","background_overlay_background":"classic","background_overlay_image":{"url":"http:\/\/fashion1.demos.shahbandr.com\/wp-content\/uploads\/sites\/4\/2021\/12\/main-image.jpeg","id":44,"alt":"","source":"library"},"background_overlay_opacity":{"unit":"px","size":1,"sizes":[]}},"elements":[{"id":"550b61e","settings":{"_column_size":50,"_inline_size":null},"elements":[],"isInner":false,"elType":"column"},{"id":"77307628","settings":{"_column_size":50,"_inline_size":null},"elements":[{"id":"7722d165","settings":{"title":"\u0625\u0643\u062a\u0634\u0641 \u0645\u0648\u062f\u064a\u0644\u0627\u062a \u0627\u0644\u0635\u064a\u0641 \u0627\u0644\u062c\u062f\u064a\u062f\u0629","align":"left","title_color":"#FFFFFF","typography_typography":"custom","typography_font_family":"Cairo","typography_font_size":{"unit":"px","size":20,"sizes":[]},"typography_font_weight":"700","etheme_parallax_scroll_y":-80},"elements":[],"isInner":false,"widgetType":"heading","elType":"widget"},{"id":"69c1ae1b","settings":{"title":"\u062e\u0635\u0648\u0645\u0627\u062a \u0627\u0644\u0635\u064a\u0641","align":"left","title_color":"#FFFFFF","typography_typography":"custom","typography_font_family":"Cairo","typography_font_size":{"unit":"px","size":80,"sizes":[]},"typography_font_weight":"700","typography_line_height":{"unit":"px","size":100,"sizes":[]},"etheme_parallax_scroll_y":-80},"elements":[],"isInner":false,"widgetType":"heading","elType":"widget"},{"id":"7582f6f6","settings":{"text":"\u062a\u0633\u0648\u0642 \u0627\u0644\u0622\u0646","align":"left","typography_typography":"custom","typography_font_family":"Cairo","typography_font_size":{"unit":"px","size":18,"sizes":[]},"typography_font_weight":"700","button_text_color":"#FFFFFF","background_color":"#000000","hover_color":"#000000","fill_hover_color":"#E0E0E0","text_padding":{"unit":"px","top":"16","right":"60","bottom":"16","left":"60","isLinked":false},"etheme_parallax_scroll_y":-80,"_padding":{"unit":"px","top":"40","right":"0","bottom":"0","left":"0","isLinked":false}},"elements":[],"isInner":false,"widgetType":"text_button","elType":"widget"}],"isInner":false,"elType":"column"}],"isInner":false,"elType":"section"}],"page_settings":[],"version":"0.4","title":"home","type":"page"}